[
  {
    "topic_id": 169393,
    "topic_title": "Thursday live session",
    "category_id": 34,
    "tags": [
      "diploma-level"
    ],
    "post_id": 604398,
    "post_number": 1,
    "author": "23f3003871",
    "created_at": "2025-03-08T06:07:14.149Z",
    "updated_at": "2025-03-08T06:07:14.149Z",
    "reply_to_post_number": null,
    "is_reply": false,
    "reply_count": 0,
    "like_count": 0,
    "is_accepted_answer": false,
    "mentioned_users": [],
    "url": "https://discourse.onlinedegree.iitm.ac.in/t/thursday-live-session/169393/1",
    "main_thread_url": "https://discourse.onlinedegree.iitm.ac.in/t/thursday-live-session/169393",
    "content": "Was the Thursday session recorded? If yes, it is not on the YouTube channel. Please provide the link.",
    "images": []
  },
  {
    "topic_id": 169393,
    "topic_title": "Thursday live session",
    "category_id": 34,
    "tags": [
      "diploma-level"
    ],
    "post_id": 604749,
    "post_number": 3,
    "author": "Yogesh1",
    "created_at": "2025-03-09T07:32:26.910Z",
    "updated_at": "2025-03-09T07:32:26.910Z",
    "reply_to_post_number": null,
    "is_reply": false,
    "reply_count": 0,
    "like_count": 0,
    "is_accepted_answer": false,
    "mentioned_users": [],
    "url": "https://discourse.onlinedegree.iitm.ac.in/t/thursday-live-session/169393/3",
    "main_thread_url": "https://discourse.onlinedegree.iitm.ac.in/t/thursday-live-session/169393",
    "content": "\n\n\n\n\n",
    "images": [
      "https://europe1.discourse-cdn.com/flex013/uploads/iitm/original/3X/a/1/a1ba40c716051f486e2fb3eaae126c6121075f69.jpeg"
    ],
    "image_descriptions": [
      {
        "url": "https://europe1.discourse-cdn.com/flex013/uploads/iitm/original/3X/a/1/a1ba40c716051f486e2fb3eaae126c6121075f69.jpeg",
        "description": "The image displays an infographic announcing \"Week 4 Session 4,\" surrounded by various colorful icons representing data visualizations, including charts, graphs, and diagrams.  No questions, scoreboards, or submission portals are present."
      }
    ]
  }
]